ipypdf/__init__.py
ipypdf/__main__.py
ipypdf/app.py
ipypdf/notebooks/API_Usage.ipynb
ipypdf/notebooks/Automation.ipynb
ipypdf/notebooks/iPyPDF.ipynb
ipypdf/style/__init__.py
ipypdf/style/style.css
ipypdf/style/style.py
ipypdf/utils/__init__.py
ipypdf/utils/constants.py
ipypdf/utils/image_utils.py
ipypdf/utils/lp_util.py
ipypdf/utils/nlp.py
ipypdf/utils/table_extraction.py
ipypdf/utils/tess_utils.py
ipypdf/utils/tree_utils.py
ipypdf/widgets/__init__.py
ipypdf/widgets/better_tree.py
ipypdf/widgets/canvas.py
ipypdf/widgets/dataframe_widget.py
ipypdf/widgets/helper_widgets.py
ipypdf/widgets/navigation.py
ipypdf/widgets/node_tools.py
ipypdf-0.1.7.dist-info/LICENSE
ipypdf-0.1.7.dist-info/METADATA
ipypdf-0.1.7.dist-info/WHEEL
ipypdf-0.1.7.dist-info/top_level.txt
ipypdf-0.1.7.dist-info/RECORD
