Metadata-Version: 2.1
Name: ipypdf
Version: 0.1.7
Summary: Jupyter widget for applying nlp to pdf documents
Home-page: https://github.com/JoelStansbury/ipypdf
Author: Joel Stansbury
Author-email: stansbury.joel@gmail.com
License: MIT
Keywords: ipypdf
Classifier: Programming Language :: Python :: 3.6
Classifier: Programming Language :: Python :: 3.7
Classifier: Programming Language :: Python :: 3.8
License-File: LICENSE
Requires-Dist: pytesseract
Requires-Dist: spacy
Requires-Dist: ipycanvas
Requires-Dist: ipycytoscape
Requires-Dist: ipyevents
Requires-Dist: ipywidgets
Requires-Dist: traitlets
Requires-Dist: numpy (<=1.19.2,>=1.13)
Requires-Dist: pillow (<=9.0.0)
Requires-Dist: pdf2image
Requires-Dist: protobuf (<=3.20)
Requires-Dist: layoutparser[paddledetection]
